pymov/__init__.py
pymov/__main__.py
pymov/py.typed
pymov/pymov.py
pymov-0.0.4.dist-info/LICENSE
pymov-0.0.4.dist-info/METADATA
pymov-0.0.4.dist-info/WHEEL
pymov-0.0.4.dist-info/entry_points.txt
pymov-0.0.4.dist-info/RECORD
