Metadata-Version: 2.1
Name: pymov
Version: 0.0.4
Summary: Pymov
Home-page: https://github.com/nanosystemslab/pymov
License: GPL-3.0
Author: Nanosystems Lab
Author-email: fnslab@hawaii.edu
Requires-Python: >=3.9,<4.0
Classifier: Development Status :: 5 - Production/Stable
Classifier: License :: OSI Approved :: GNU General Public License v3 (GPLv3)
Classifier: Programming Language :: Python :: 3
Classifier: Programming Language :: Python :: 3.9
Classifier: Programming Language :: Python :: 3.10
Classifier: Programming Language :: Python :: 3.11
Classifier: Programming Language :: Python :: 3.12
Requires-Dist: argparse (>=1.4.0)
Requires-Dist: pyserial (>=3.5,<4.0)
Requires-Dist: types-pyserial (>=3.5.0.20240826,<4.0.0.0)
Project-URL: Changelog, https://github.com/nanosystemslab/pymov/releases
Project-URL: Documentation, https://pymov.readthedocs.io
Project-URL: Repository, https://github.com/nanosystemslab/pymov
